myproxy/__init__.py
myproxy/myproxy.py
myproxy_8680-1.0.1.dist-info/LICENSE
myproxy_8680-1.0.1.dist-info/METADATA
myproxy_8680-1.0.1.dist-info/WHEEL
myproxy_8680-1.0.1.dist-info/top_level.txt
myproxy_8680-1.0.1.dist-info/RECORD
