Metadata-Version: 2.1
Name: myproxy_8680
Version: 1.0.1
Summary: get A max heath proxy
Author-email: dong lin <15241848680@163.com>
Project-URL: Homepage, https://github.com/lindong8680/myproxy
Project-URL: Issues, https://github.com/lindong8680/myproxy/issues
Classifier: Programming Language :: Python :: 3
Classifier: License :: OSI Approved :: MIT License
Classifier: Operating System :: OS Independent
Requires-Python: >=3.6
License-File: LICENSE
